hystore/__init__.py
hystore/contrib/__init__.py
hystore/contrib/check_postcodes.py
hystore/contrib/dataset_parameters.py
hystore/contrib/diet_analysis.py
hystore/contrib/export_diet_dataset.py
hystore/contrib/other_symptoms.py
hystore/contrib/supplement_paper_processing.py
hystore/core/__init__.py
hystore/core/data_schema.py
hystore/core/dataset.py
hystore/core/exporter.py
hystore/core/fields.py
hystore/core/filtered_field.py
hystore/core/importer.py
hystore/core/load_schema.py
hystore/core/operations.py
hystore/core/persistence.py
hystore/core/readerwriter.py
hystore/core/regression.py
hystore/core/session.py
hystore/core/split.py
hystore/core/utils.py
hystore/core/validation.py
hystore/covidspecific/__init__.py
hystore/covidspecific/geo_mismatches.py
hystore/covidspecific/parsing_schemas.py
hystore/covidspecific/pipeline.py
hystore/covidspecific/postprocess.py
hystore/covidspecific/process_tests.py
hystore/covidspecific/utils.py
hystore/covidspecific/validate.py
hystore/processing/__init__.py
hystore/processing/age_from_year_of_birth.py
hystore/processing/analytics.py
hystore/processing/assessment_merge.py
hystore/processing/combined_healthcare_worker.py
hystore/processing/consolidated_test_dates.py
hystore/processing/convert_old_assessments.py
hystore/processing/covid_test.py
hystore/processing/effective_test_date.py
hystore/processing/healthy_diet_index.py
hystore/processing/inconsistent_symptoms.py
hystore/processing/inconsistent_testing.py
hystore/processing/method_paper_model.py
hystore/processing/nat_medicine_model.py
hystore/processing/numpy_buffer.py
hystore/processing/temperature.py
hystore/processing/test_type_from_mechanism.py
hystore/processing/weight_height_bmi.py
hystore-0.2.7.3.data/scripts/hystorex
hystore-0.2.7.3.dist-info/LICENSE.txt
hystore-0.2.7.3.dist-info/METADATA
hystore-0.2.7.3.dist-info/WHEEL
hystore-0.2.7.3.dist-info/top_level.txt
hystore-0.2.7.3.dist-info/RECORD
