Metadata-Version: 2.1
Name: hystore
Version: 0.2.7.3
Summary: High-volume key-value store and analytics, based on hdf5
Home-page: https://github.com/kcl-bmeis/zoe-data-store
Author: Ben Murray
Author-email: benjamin.murray@kcl.ac.uk
License: http://www.apache.org/licenses/LICENSE-2.0
Platform: UNKNOWN
Requires-Dist: numpy
Requires-Dist: numba
Requires-Dist: pandas
Requires-Dist: h5py
